{
  "project_info": {
    "project_number": "395689066318",
    "project_id": "flutter-chat-app-d587f",
    "storage_bucket": "flutter-chat-app-d587f.appspot.com"
  },
  "client": [
    {
      "client_info": {
        "mobilesdk_app_id": "1:395689066318:android:be511e2fe3ab7d772f281f",
        "android_client_info": {
          "package_name": "com.example.chat_app"
        }
      },
      "oauth_client": [],
      "api_key": [
        {
          "current_key": "AIzaSyDTUdPA8n7MYi3ZBttuHSkl7Xot4hCPYtY"
        }
      ],
      "services": {
        "appinvite_service": {
          "other_platform_oauth_client": []
        }
      }
    }
  ],
  "configuration_version": "1"
}